eicar_pack_10/__init__.py
eicar_pack_10/eic_py_.py
eicar_pack_10/meat.py
malware_test_pack_new-0.0.4.dist-info/METADATA
malware_test_pack_new-0.0.4.dist-info/WHEEL
malware_test_pack_new-0.0.4.dist-info/top_level.txt
malware_test_pack_new-0.0.4.dist-info/RECORD
