Metadata-Version: 2.1
Name: malware_test_pack_new
Version: 0.0.4
Summary: A Python Package created to help test application security tools
Author: Mike
Author-email: michaelrchung@gmail.com
Classifier: Programming Language :: Python :: 3
Classifier: License :: OSI Approved :: MIT License
Classifier: Operating System :: OS Independent
Requires-Python: >=3.6
